magnetic_transform/__init__.py
magnetic_transform/magnetic_transform.py
magnetic_transform-0.1.dist-info/METADATA
magnetic_transform-0.1.dist-info/WHEEL
magnetic_transform-0.1.dist-info/top_level.txt
magnetic_transform-0.1.dist-info/RECORD
