Metadata-Version: 2.1
Name: magnetic-transform
Version: 0.1
Summary: A library for magnetic field transformation
Home-page: https://github.com/yourusername/magnetic_transform
Author: Your Name
Author-email: your.email@example.com
Classifier: Programming Language :: Python :: 3
Classifier: License :: OSI Approved :: MIT License
Classifier: Operating System :: OS Independent
Requires-Python: >=3.6
Requires-Dist: numpy
Requires-Dist: scipy
